attribdict/AttribDict.py
attribdict/__init__.py
attribdict-0.0.5.dist-info/LICENSE
attribdict-0.0.5.dist-info/METADATA
attribdict-0.0.5.dist-info/WHEEL
attribdict-0.0.5.dist-info/top_level.txt
attribdict-0.0.5.dist-info/RECORD
