Metadata-Version: 2.1
Name: attribdict
Version: 0.0.5
Summary: An easy to use and easy to read dict
Home-page: https://github.com/yiqunchen1999/attribdict
Author: Yiqun Chen
Author-email: yiqunchen1999@gmail.com
License: UNKNOWN
Platform: UNKNOWN
Classifier: Programming Language :: Python :: 3
Classifier: License :: OSI Approved :: MIT License
Classifier: Operating System :: OS Independent
